{
  "indexes": [
    {
      "collectionGroup": "users",
      "queryScope": "COLLECTION",
      "fields": [
        { "fieldPath": "schoolId", "order": "ASCENDING" },
        { "fieldPath": "displayName", "order": "ASCENDING" }
      ]
    },
    {
      "collectionGroup": "users",
      "queryScope": "COLLECTION",
      "fields": [
        { "fieldPath": "schoolId", "order": "ASCENDING" },
        { "fieldPath": "role", "order": "ASCENDING" },
        { "fieldPath": "displayName", "order": "ASCENDING" }
      ]
    },
    {
      "collectionGroup": "assignments",
      "queryScope": "COLLECTION",
      "fields": [
        { "fieldPath": "schoolId", "order": "ASCENDING" },
        { "fieldPath": "dueDate", "order": "DESCENDING" }
      ]
    },
    {
      "collectionGroup": "assignments",
      "queryScope": "COLLECTION",
      "fields": [
        { "fieldPath": "schoolId", "order": "ASCENDING" },
        { "fieldPath": "classId", "order": "ASCENDING" },
        { "fieldPath": "dueDate", "order": "DESCENDING" }
      ]
    },
    {
      "collectionGroup": "marks",
      "queryScope": "COLLECTION",
      "fields": [
        { "fieldPath": "studentId", "order": "ASCENDING" },
        { "fieldPath": "year", "order": "DESCENDING" }
      ]
    },
    {
      "collectionGroup": "marks",
      "queryScope": "COLLECTION",
      "fields": [
        { "fieldPath": "studentId", "order": "ASCENDING" },
        { "fieldPath": "termId", "order": "ASCENDING" }
      ]
    },
    {
      "collectionGroup": "marks",
      "queryScope": "COLLECTION",
      "fields": [
        { "fieldPath": "schoolId", "order": "ASCENDING" },
        { "fieldPath": "subjectId", "order": "ASCENDING" },
        { "fieldPath": "termId", "order": "ASCENDING" },
        { "fieldPath": "examType", "order": "ASCENDING" }
      ]
    },
    {
      "collectionGroup": "videoLessons",
      "queryScope": "COLLECTION",
      "fields": [
        { "fieldPath": "schoolId", "order": "ASCENDING" },
        { "fieldPath": "createdAt", "order": "DESCENDING" }
      ]
    },
    {
      "collectionGroup": "videoLessons",
      "queryScope": "COLLECTION",
      "fields": [
        { "fieldPath": "schoolId", "order": "ASCENDING" },
        { "fieldPath": "classId", "order": "ASCENDING" },
        { "fieldPath": "createdAt", "order": "DESCENDING" }
      ]
    },
    {
      "collectionGroup": "submissions",
      "queryScope": "COLLECTION",
      "fields": [
        { "fieldPath": "assignmentId", "order": "ASCENDING" },
        { "fieldPath": "submittedAt", "order": "DESCENDING" }
      ]
    },
    {
      "collectionGroup": "submissions",
      "queryScope": "COLLECTION",
      "fields": [
        { "fieldPath": "studentId", "order": "ASCENDING" },
        { "fieldPath": "submittedAt", "order": "DESCENDING" }
      ]
    },
    {
      "collectionGroup": "conversations",
      "queryScope": "COLLECTION",
      "fields": [
        { "fieldPath": "participants", "arrayConfig": "CONTAINS" },
        { "fieldPath": "lastMessageAt", "order": "DESCENDING" }
      ]
    },
    {
      "collectionGroup": "notifications",
      "queryScope": "COLLECTION",
      "fields": [
        { "fieldPath": "recipientId", "order": "ASCENDING" },
        { "fieldPath": "createdAt", "order": "DESCENDING" }
      ]
    },
    {
      "collectionGroup": "projects",
      "queryScope": "COLLECTION",
      "fields": [
        { "fieldPath": "schoolId", "order": "ASCENDING" },
        { "fieldPath": "dueDate", "order": "DESCENDING" }
      ]
    },
    {
      "collectionGroup": "projects",
      "queryScope": "COLLECTION",
      "fields": [
        { "fieldPath": "studentIds", "arrayConfig": "CONTAINS" },
        { "fieldPath": "dueDate", "order": "DESCENDING" }
      ]
    },
    {
      "collectionGroup": "projects",
      "queryScope": "COLLECTION",
      "fields": [
        { "fieldPath": "teacherId", "order": "ASCENDING" },
        { "fieldPath": "dueDate", "order": "DESCENDING" }
      ]
    },
    {
      "collectionGroup": "fees",
      "queryScope": "COLLECTION",
      "fields": [
        { "fieldPath": "schoolId", "order": "ASCENDING" },
        { "fieldPath": "createdAt", "order": "DESCENDING" }
      ]
    },
    {
      "collectionGroup": "fees",
      "queryScope": "COLLECTION",
      "fields": [
        { "fieldPath": "studentId", "order": "ASCENDING" },
        { "fieldPath": "createdAt", "order": "DESCENDING" }
      ]
    },
    {
      "collectionGroup": "fees",
      "queryScope": "COLLECTION",
      "fields": [
        { "fieldPath": "schoolId", "order": "ASCENDING" },
        { "fieldPath": "termId", "order": "ASCENDING" },
        { "fieldPath": "createdAt", "order": "DESCENDING" }
      ]
    },
    {
      "collectionGroup": "announcements",
      "queryScope": "COLLECTION",
      "fields": [
        { "fieldPath": "schoolId", "order": "ASCENDING" },
        { "fieldPath": "createdAt", "order": "DESCENDING" }
      ]
    },
    {
      "collectionGroup": "timetable",
      "queryScope": "COLLECTION",
      "fields": [
        { "fieldPath": "classId", "order": "ASCENDING" },
        { "fieldPath": "day", "order": "ASCENDING" },
        { "fieldPath": "startTime", "order": "ASCENDING" }
      ]
    }
  ],
  "fieldOverrides": []
}
